hilookup/__init__.py
hilookup/helper.py
hilookup/hilookup.py
hilookup-0.1.1.dist-info/LICENSE
hilookup-0.1.1.dist-info/METADATA
hilookup-0.1.1.dist-info/WHEEL
hilookup-0.1.1.dist-info/top_level.txt
hilookup-0.1.1.dist-info/RECORD
