Metadata-Version: 2.1
Name: hilookup
Version: 0.1.1
Summary: A module for fuzzy lookup that provides more controls to users.
Author: Tomex Iskandar
Author-email: tomex.iskandar@gmail.com
Keywords: data quality tool
License-File: LICENSE
